better_automation/__init__.py
better_automation/google/__init__.py
better_automation/google/account.py
better_automation/google/browser.py
better_automation/google/errors.py
better_automation/google/utils.py
better_automation/googleapis/__init__.py
better_automation/googleapis/client.py
better_automation/googleapis/errors.py
better_automation/googleapis/models.py
better_automation/playwright_.py
better_automation/smshub/__init__.py
better_automation/smshub/client.py
better_automation/smshub/errors.py
better_automation-3.0.6.dist-info/METADATA
better_automation-3.0.6.dist-info/WHEEL
better_automation-3.0.6.dist-info/RECORD
