Metadata-Version: 2.1
Name: better-automation
Version: 3.0.6
Summary: tweepy-self, Google, googleapis, smshub
Home-page: https://github.com/alenkimov/better_automation
Author: Alen
Author-email: alen.kimov@gmail.com
Requires-Python: >=3.11,<4.0
Classifier: Programming Language :: Python :: 3
Classifier: Programming Language :: Python :: 3.11
Classifier: Programming Language :: Python :: 3.12
Requires-Dist: playwright-stealth (>=1,<2)
Requires-Dist: tweepy-self (>=1,<2)
Project-URL: Repository, https://github.com/alenkimov/better_automation
Project-URL: Source, https://github.com/alenkimov/better_automation
